{"identity":"CharacterGeneratorSettings","version":"2.0.0","gender":"female","patterns":{"body":"p01","face":"p03","fronthair":"p16","rearhair":"p11","ears":"p01","eyes":"p07","eyebrows":"p04","nose":"p19","mouth":"p01","facialmark":"","beastears":"","clothing":"p08","acca":"p03","accb":"p06"},"colors":{"#F9C19D":5,"#2C80CB":6,"#FCCB0A":5,"#B892C5":12,"#009296":1,"#D3CEC7":22,"#AE8682":16,"#FE9D1E":17,"#1C76D0":0,"#D9A404":0,"#D8AC00":5,"#A30708":0,"#D3CEC2":2,"#DA346E":1,"#A4C911":0,"#C78407":16,"#C0D3D2":16,"#4155B6":2,"#BA3B45":5,"#999999":14,"#CCBAD2":0,"#607E4B":13,"#E6D6BD":4,"#A7D6D6":15},"offsets":{"face":{"x":0,"y":0},"fronthair":{"x":0,"y":0},"rearhair":{"x":0,"y":0},"beard":{"x":0,"y":0},"ears":{"x":0,"y":0},"eyes":{"x":0,"y":0},"eyebrows":{"x":0,"y":0},"nose":{"x":0,"y":0},"mouth":{"x":0,"y":0},"facialmark":{"x":0,"y":0},"beastears":{"x":0,"y":0},"tail":{"x":0,"y":0},"wing":{"x":0,"y":0},"clothing":{"x":0,"y":0},"cloak":{"x":0,"y":0},"acca":{"x":0,"y":0},"accb":{"x":0,"y":0},"glasses":{"x":0,"y":0}}}