{"identity":"CharacterGeneratorSettings","version":"2.0.0","gender":"male","patterns":{"body":"p01","face":"p05","fronthair":"p06","rearhair":"p16","ears":"p01","eyes":"p01","eyebrows":"p18","nose":"p04","mouth":"p16","clothing":"p26","glasses":"p05"},"colors":{"#F9C19D":5,"#2C80CB":4,"#FCCB0A":18,"#B892C5":7,"#009296":0,"#D3CEC7":10,"#AE8682":0,"#FE9D1E":1,"#1C76D0":0,"#D9A404":0,"#D8AC00":11,"#A30708":0,"#D3CEC2":0,"#DA346E":0,"#A4C911":0,"#C78407":14,"#C0D3D2":0,"#4155B6":0,"#BA3B45":0,"#999999":7,"#CCBAD2":16,"#607E4B":0,"#E6D6BD":22,"#A7D6D6":13},"offsets":{"face":{"x":0,"y":0},"fronthair":{"x":0,"y":0},"rearhair":{"x":0,"y":0},"beard":{"x":0,"y":0},"ears":{"x":0,"y":0},"eyes":{"x":0,"y":0},"eyebrows":{"x":0,"y":0},"nose":{"x":0,"y":0},"mouth":{"x":0,"y":0},"facialmark":{"x":0,"y":0},"beastears":{"x":0,"y":0},"tail":{"x":0,"y":0},"wing":{"x":0,"y":0},"clothing":{"x":0,"y":0},"cloak":{"x":0,"y":0},"acca":{"x":0,"y":0},"accb":{"x":0,"y":0},"glasses":{"x":0,"y":0}}}